dengta/__init__.py
dengta/func.py
dengta-1.0.dist-info/LICENCE
dengta-1.0.dist-info/METADATA
dengta-1.0.dist-info/WHEEL
dengta-1.0.dist-info/top_level.txt
dengta-1.0.dist-info/RECORD
